{"IcoMoonType":"selection","icons":[{"icon":{"paths":["M102.39 819.22v102.588h204.879v-102.588h-204.879zM102.39 614.44v102.39h512.149v-102.291h-512.149zM409.659 819.319v102.489h204.879v-102.588h-204.929zM716.879 614.44v102.39h204.929v-102.291h-204.978zM716.83 819.319v102.489h204.978v-102.588h-204.978zM0 1024v-716.731l256.025 204.78v-204.78l256.025 204.78v-204.78l256.124 204.731 51.046-512h153.635l51.195 512v512z"],"attrs":[{}],"isMulticolor":false,"isMulticolor2":false,"grid":0,"tags":["industry"]},"attrs":[{}],"properties":{"order":3,"id":0,"name":"industry","prevSize":32,"code":59648},"setIdx":0,"setId":4,"iconIdx":0}],"height":1024,"metadata":{"name":"icomoon"},"preferences":{"showGlyphs":true,"showQuickUse":true,"showQuickUse2":false,"showSVGs":true,"fontPref":{"prefix":"icon-","metadata":{"fontFamily":"icomoon"},"metrics":{"emSize":1024,"baseline":6.25,"whitespace":50},"embed":false,"autoHost":true},"imagePref":{"prefix":"icon-","png":true,"useClassSelector":true,"color":0,"bgColor":16777215,"classSelector":".icon","name":"icomoon","autoHost":true},"historySize":50,"showCodes":true,"gridSize":16,"quickUsageToken":{"prueba1":"YjlmZWRhYmJkNDQ4YTNhMTU2NTNhNDRkZTlmZTZkYTMjMSMxNTQ0MjAzNjg3IyMj"}}}